floatapp/__init__.py
floatapp/endpoints.py
floatapp/jsonp.py
floatapp/login.py
floatapp/process.py
myphotoshare-6.0.2.dist-info/LICENSE
myphotoshare-6.0.2.dist-info/METADATA
myphotoshare-6.0.2.dist-info/WHEEL
myphotoshare-6.0.2.dist-info/top_level.txt
myphotoshare-6.0.2.dist-info/RECORD
