Metadata-Version: 2.1
Name: myphotoshare
Version: 6.0.2
Summary: A Static Web Photo Gallery with Advanced Features
Home-page: https://gitlab.com/paolobenve/myphotoshare
Author: Paolo Benvenuto
Author-email: paolobenve@gmail.com
License: UNKNOWN
Project-URL: Bug Reports, https://gitlab.com/paolobenve/myphotosharet/issues
Project-URL: Source, https://gitlab.com/paolobenve/myphotoshare
Keywords: gallery,photos,json
Platform: UNKNOWN
Classifier: Development Status :: 5 - Production/Stable
Classifier: Intended Audience :: Developers
Classifier: Topic :: Multimedia :: Graphics :: Viewers
Classifier: License :: OSI Approved :: GNU General Public License v3 (GPLv3)
Classifier: Programming Language :: Python :: 3
Classifier: Programming Language :: Python :: 3.7
Classifier: Programming Language :: Python :: 3.8
Classifier: Programming Language :: Python :: 3.9
Classifier: Programming Language :: Python :: 3.10
Classifier: Programming Language :: Python :: 3 :: Only
Requires-Python: >=3.7, <4
License-File: LICENSE
Requires-Dist: python-magic
Requires-Dist: numpy
Requires-Dist: requests
Requires-Dist: Pillow
Requires-Dist: Unidecode
Requires-Dist: exif
Requires-Dist: pillow-avif-plugin
Requires-Dist: opencv-python
Provides-Extra: dev
Requires-Dist: check-manifest ; extra == 'dev'
Provides-Extra: test
Requires-Dist: coverage ; extra == 'test'
